{"song":{"keyCount":16,"player1":"bf","modchartPath":"bean","chartOffset":0,"playerKeyCount":16,"notes":[{"sectionNotes":[[0,7,0,0,"default"],[150,11,0,0,"default"],[300,4,0,0,"default"],[450,5,0,0,"default"],[750,10,0,0,"default"],[900,7,0,0,"default"],[1050,4,0,0,"default"],[1125,5,0,0,"default"]],"lengthInSteps":16,"bpm":0.1,"mustHitSection":false},{"sectionNotes":[[1200,11,0,0,"default"],[1275,8,0,0,"default"],[1350,7,0,0,"default"],[1425,4,0,0,"default"],[1500,8,0,0,"default"],[1575,10,0,0,"default"],[1650,4,0,0,"default"],[1800,5,0,0,"default"],[1950,9,0,0,"default"],[2100,11,0,0,"default"],[2250,8,0,0,"default"]],"lengthInSteps":16,"bpm":0.1,"mustHitSection":false},{"sectionNotes":[[2400,7,0,0,"default"],[2550,11,0,0,"default"],[2700,4,0,0,"default"],[2850,5,0,0,"default"],[3150,10,0,0,"default"],[3300,7,0,0,"default"],[3450,4,0,0,"default"],[3525,5,0,0,"default"]],"lengthInSteps":16,"bpm":0.1,"mustHitSection":true},{"sectionNotes":[[3600,11,0,0,"default"],[3675,8,0,0,"default"],[3750,7,0,0,"default"],[3825,4,0,0,"default"],[3900,8,0,0,"default"],[3975,10,0,0,"default"],[4050,4,0,0,"default"],[4200,5,0,0,"default"],[4350,9,0,0,"default"],[4500,11,0,0,"default"],[4650,8,0,0,"default"]],"lengthInSteps":16,"bpm":0.1,"mustHitSection":true},{"sectionNotes":[[4800,5,0,1,"default"],[4950,7,0,1,"default"],[5100,9,0,1,"default"],[5250,7,0,1,"default"],[5550,10,0,1,"default"],[5700,11,0,1,"default"],[5850,5,0,1,"default"],[5925,8,0,1,"default"]],"lengthInSteps":16,"bpm":0.1,"mustHitSection":false},{"sectionNotes":[[6000,4,0,1,"default"],[6075,7,0,1,"default"],[6150,8,0,1,"default"],[6225,11,0,1,"default"],[6300,8,0,1,"default"],[6375,7,0,1,"default"],[6450,10,0,1,"default"],[6600,6,0,1,"default"],[6750,10,0,1,"default"],[6900,5,0,1,"default"],[7050,9,0,1,"default"]],"lengthInSteps":16,"bpm":0.1,"mustHitSection":false},{"sectionNotes":[[7200,5,0,1,"default"],[7350,7,0,1,"default"],[7500,9,0,1,"default"],[7650,7,0,1,"default"],[7950,10,0,1,"default"],[8100,11,0,1,"default"],[8250,5,0,1,"default"],[8325,8,0,1,"default"]],"lengthInSteps":16,"bpm":0.1,"mustHitSection":true},{"sectionNotes":[[8400,4,0,1,"default"],[8475,7,0,1,"default"],[8550,8,0,1,"default"],[8625,11,0,1,"default"],[8700,8,0,1,"default"],[8775,7,0,1,"default"],[8850,10,0,1,"default"],[9000,6,0,1,"default"],[9150,10,0,1,"default"],[9300,5,0,1,"default"],[9450,9,0,1,"default"]],"lengthInSteps":16,"bpm":0.1,"mustHitSection":true},{"sectionNotes":[[9600,9,0,0,"default"],[9750,11,0,0,"default"],[9900,10,0,0,"default"],[10050,8,0,0,"default"],[10350,11,0,0,"default"],[10500,8,0,0,"default"],[10650,10,0,0,"default"],[9600,5,0,1,"default"],[9750,7,0,1,"default"],[9900,5,0,1,"default"],[10050,6,0,1,"default"],[10350,6,0,1,"default"],[10500,4,0,1,"default"],[10650,6,0,1,"default"]],"lengthInSteps":16,"bpm":0.1,"mustHitSection":false},{"sectionNotes":[[10800,8,0,0,"default"],[10950,10,0,0,"default"],[11100,11,0,0,"default"],[11250,9,0,0,"default"],[11550,8,0,0,"default"],[11700,10,0,0,"default"],[11850,8,0,0,"default"],[10800,7,0,1,"default"],[10950,4,0,1,"default"],[11100,7,0,1,"default"],[11250,5,0,1,"default"],[11550,7,0,1,"default"],[11700,5,0,1,"default"],[11850,6,0,1,"default"]],"lengthInSteps":16,"bpm":0.1,"mustHitSection":false},{"sectionNotes":[[12000,9,0,0,"default"],[12150,11,0,0,"default"],[12300,10,0,0,"default"],[12450,8,0,0,"default"],[12750,11,0,0,"default"],[12900,8,0,0,"default"],[13050,10,0,0,"default"],[12000,5,0,1,"default"],[12150,7,0,1,"default"],[12300,5,0,1,"default"],[12450,6,0,1,"default"],[12750,6,0,1,"default"],[12900,4,0,1,"default"],[13050,6,0,1,"default"]],"lengthInSteps":16,"bpm":0.1,"mustHitSection":true},{"sectionNotes":[[13200,8,0,0,"default"],[13350,10,0,0,"default"],[13500,11,0,0,"default"],[13650,9,0,0,"default"],[13950,8,0,0,"default"],[14100,10,0,0,"default"],[14250,8,0,0,"default"],[13200,7,0,1,"default"],[13350,4,0,1,"default"],[13500,7,0,1,"default"],[13650,5,0,1,"default"],[13950,7,0,1,"default"],[14100,5,0,1,"default"],[14250,6,0,1,"default"]],"lengthInSteps":16,"bpm":0.1,"mustHitSection":true},{"sectionNotes":[[14400,9,0,0,"default"],[14550,11,0,0,"default"],[14700,10,0,0,"default"],[14850,8,0,0,"default"],[15150,11,0,0,"default"],[15300,8,0,0,"default"],[15450,10,0,0,"default"],[14400,5,0,1,"default"],[14550,7,0,1,"default"],[14700,5,0,1,"default"],[14850,6,0,1,"default"],[15150,6,0,1,"default"],[15300,4,0,1,"default"],[15450,6,0,1,"default"]],"lengthInSteps":16,"bpm":0.1,"mustHitSection":false},{"sectionNotes":[[15600,8,0,0,"default"],[15750,10,0,0,"default"],[15900,11,0,0,"default"],[16050,9,0,0,"default"],[16350,8,0,0,"default"],[16500,10,0,0,"default"],[16650,8,0,0,"default"],[15600,7,0,1,"default"],[15750,4,0,1,"default"],[15900,7,0,1,"default"],[16050,5,0,1,"default"],[16350,7,0,1,"default"],[16500,5,0,1,"default"],[16650,6,0,1,"default"]],"lengthInSteps":16,"bpm":0.1,"mustHitSection":false},{"sectionNotes":[[16800,9,0,0,"default"],[16950,11,0,0,"default"],[17100,10,0,0,"default"],[17250,8,0,0,"default"],[17550,11,0,0,"default"],[17700,8,0,0,"default"],[17850,10,0,0,"default"],[16800,5,0,1,"default"],[16950,7,0,1,"default"],[17100,5,0,1,"default"],[17250,6,0,1,"default"],[17550,6,0,1,"default"],[17700,4,0,1,"default"],[17850,6,0,1,"default"]],"lengthInSteps":16,"bpm":0.1,"mustHitSection":true},{"sectionNotes":[[18000,8,0,0,"default"],[18150,10,0,0,"default"],[18300,11,0,0,"default"],[18450,9,0,0,"default"],[18750,8,0,0,"default"],[18900,10,0,0,"default"],[19050,8,0,0,"default"],[18000,7,0,1,"default"],[18150,4,0,1,"default"],[18300,7,0,1,"default"],[18450,5,0,1,"default"],[18600,6,0,1,"default"],[18750,4,0,1,"default"],[18900,5,0,1,"default"],[19050,7,225,1,"default"]],"lengthInSteps":16,"bpm":0.1,"mustHitSection":true},{"sectionNotes":[[19200,10,0,0,"default"],[19350,11,0,0,"default"],[19650,5,0,0,"default"],[19800,4,0,0,"default"],[19950,5,0,0,"default"],[20100,8,225,0,"default"]],"lengthInSteps":16,"bpm":0.1,"mustHitSection":false},{"sectionNotes":[[20400,5,0,0,"default"],[20550,9,0,0,"default"],[20850,10,0,0,"default"],[21000,8,0,0,"default"],[21150,6,0,0,"default"],[21300,7,0,0,"default"],[21450,6,0,0,"default"]],"lengthInSteps":16,"bpm":0.1,"mustHitSection":false},{"sectionNotes":[[21600,5,0,0,"default"],[21750,9,0,0,"default"],[21900,8,0,0,"default"],[22050,7,0,0,"default"],[22200,4,225,0,"default"],[22500,5,225,0,"default"]],"lengthInSteps":16,"bpm":0.1,"mustHitSection":false},{"sectionNotes":[[22800,10,0,0,"default"],[22875,6,0,0,"default"],[22950,9,0,0,"default"],[23025,5,0,0,"default"],[23100,10,0,0,"default"],[23175,6,0,0,"default"],[23250,9,0,0,"default"],[23325,5,0,0,"default"],[23400,8,225,0,"default"],[23700,7,225,0,"default"]],"lengthInSteps":16,"bpm":0.1,"mustHitSection":false},{"sectionNotes":[[24000,10,0,0,"default"],[24150,11,0,0,"default"],[24450,5,0,0,"default"],[24600,4,0,0,"default"],[24750,5,0,0,"default"],[24900,8,225,0,"default"]],"lengthInSteps":16,"bpm":0.1,"mustHitSection":true},{"sectionNotes":[[25200,5,0,0,"default"],[25350,9,0,0,"default"],[25650,10,0,0,"default"],[25800,8,0,0,"default"],[25950,6,0,0,"default"],[26100,7,0,0,"default"],[26250,6,0,0,"default"]],"lengthInSteps":16,"bpm":0.1,"mustHitSection":true},{"sectionNotes":[[26400,5,0,0,"default"],[26550,9,0,0,"default"],[26700,8,0,0,"default"],[26850,7,0,0,"default"],[27000,4,225,0,"default"],[27300,5,225,0,"default"]],"lengthInSteps":16,"bpm":0.1,"mustHitSection":true},{"sectionNotes":[[27600,10,0,0,"default"],[27675,6,0,0,"default"],[27750,9,0,0,"default"],[27825,5,0,0,"default"],[27900,10,0,0,"default"],[27975,6,0,0,"default"],[28050,9,0,0,"default"],[28125,5,0,0,"default"],[28200,8,225,0,"default"],[28500,7,225,0,"default"]],"lengthInSteps":16,"bpm":0.1,"mustHitSection":true},{"sectionNotes":[[28800,5,0,1,"default"],[28950,10,0,1,"default"],[29100,7,0,1,"default"],[29250,8,0,1,"default"],[29400,5,0,1,"default"],[29550,10,0,1,"default"],[29700,7,0,1,"default"],[29850,10,0,1,"default"]],"lengthInSteps":16,"bpm":0.1,"mustHitSection":false},{"sectionNotes":[[30000,6,0,1,"default"],[30075,4,0,1,"default"],[30150,7,0,1,"default"],[30225,5,0,1,"default"],[30300,10,0,1,"default"],[30375,8,0,1,"default"],[30450,11,0,1,"default"],[30525,9,0,1,"default"],[30600,6,225,1,"default"],[30900,7,225,1,"default"]],"lengthInSteps":16,"bpm":0.1,"mustHitSection":false},{"sectionNotes":[[31200,9,375,1,"default"],[31650,7,375,1,"default"],[32100,4,225,1,"default"]],"lengthInSteps":16,"bpm":0.1,"mustHitSection":false},{"sectionNotes":[[32400,10,225,1,"default"],[32700,7,225,1,"default"],[33000,8,0,1,"default"],[33075,11,0,1,"default"],[33150,9,0,1,"default"],[33225,11,0,1,"default"],[33300,6,0,1,"default"],[33375,4,0,1,"default"],[33450,9,0,1,"default"],[33525,4,0,1,"default"]],"lengthInSteps":16,"bpm":0.1,"mustHitSection":false},{"sectionNotes":[[33600,5,0,1,"default"],[33750,10,0,1,"default"],[33900,7,0,1,"default"],[34050,8,0,1,"default"],[34200,5,0,1,"default"],[34350,10,0,1,"default"],[34500,7,0,1,"default"],[34650,10,0,1,"default"]],"lengthInSteps":16,"bpm":0.1,"mustHitSection":true},{"sectionNotes":[[34800,6,0,1,"default"],[34875,4,0,1,"default"],[34950,7,0,1,"default"],[35025,5,0,1,"default"],[35100,10,0,1,"default"],[35175,8,0,1,"default"],[35250,11,0,1,"default"],[35325,9,0,1,"default"],[35400,6,225,1,"default"],[35700,7,225,1,"default"]],"lengthInSteps":16,"bpm":0.1,"mustHitSection":true},{"sectionNotes":[[36000,9,375,1,"default"],[36450,7,375,1,"default"],[36900,4,225,1,"default"]],"lengthInSteps":16,"bpm":0.1,"mustHitSection":true},{"sectionNotes":[[37200,10,225,1,"default"],[37500,7,225,1,"default"],[37800,8,0,1,"default"],[37875,11,0,1,"default"],[37950,9,0,1,"default"],[38025,11,0,1,"default"],[38100,6,0,1,"default"],[38175,4,0,1,"default"],[38250,9,0,1,"default"],[38325,4,0,1,"default"]],"lengthInSteps":16,"bpm":0.1,"mustHitSection":true},{"altAnim":false,"mustHitSection":false,"lengthInSteps":16,"typeOfSection":0,"sectionNotes":[[38400,9,0,0,"default"],[38550,11,0,0,"default"],[38700,10,0,0,"default"],[38850,5,0,0,"default"],[39000,4,0,0,"default"],[39150,9,0,0,"default"],[39300,7,0,0,"default"],[39450,5,0,0,"default"]],"changeTimeScale":false,"timeScale":[4,4],"changeBPM":false,"bpm":100},{"altAnim":false,"mustHitSection":false,"lengthInSteps":16,"typeOfSection":0,"sectionNotes":[[39600,9,0,0,"default"],[39675,6,0,0,"default"],[39750,7,0,0,"default"],[39825,5,0,0,"default"],[39900,10,0,0,"default"],[40050,9,0,0,"default"],[40200,11,0,0,"default"],[40350,7,0,0,"default"],[40500,5,0,0,"default"],[40650,4,0,0,"default"]],"changeTimeScale":false,"timeScale":[4,4],"changeBPM":false,"bpm":180},{"altAnim":false,"mustHitSection":false,"lengthInSteps":16,"typeOfSection":0,"sectionNotes":[[40800,6,0,0,"default"],[40950,7,0,0,"default"],[41100,8,0,0,"default"],[41250,9,0,0,"default"],[41400,11,0,0,"default"],[41550,8,0,0,"default"],[41700,7,0,0,"default"],[41850,5,0,0,"default"]],"changeTimeScale":false,"timeScale":[4,4],"changeBPM":false,"bpm":180},{"altAnim":false,"mustHitSection":false,"lengthInSteps":16,"typeOfSection":0,"sectionNotes":[[42000,4,225,0,"default"],[42300,7,0,0,"default"],[42450,8,0,0,"default"],[42600,10,0,0,"default"],[42675,8,0,0,"default"],[42750,11,0,0,"default"],[42825,9,0,0,"default"],[42900,6,0,0,"default"],[42975,4,0,0,"default"],[43050,7,0,0,"default"],[43125,5,0,0,"default"]],"changeTimeScale":false,"timeScale":[4,4],"changeBPM":false,"bpm":180},{"altAnim":false,"mustHitSection":false,"lengthInSteps":16,"typeOfSection":0,"sectionNotes":[[43200,10,225,1,"default"],[43500,8,0,1,"default"],[43650,5,0,1,"default"],[43800,8,225,1,"default"],[44100,9,225,1,"default"]],"changeTimeScale":false,"timeScale":[4,4],"changeBPM":false,"bpm":180},{"altAnim":false,"mustHitSection":false,"lengthInSteps":16,"typeOfSection":0,"sectionNotes":[[44400,7,0,1,"default"],[44550,6,0,1,"default"],[44700,7,0,1,"default"],[44850,9,0,1,"default"],[45000,4,0,1,"default"],[45300,8,0,1,"default"]],"changeTimeScale":false,"timeScale":[4,4],"changeBPM":false,"bpm":180},{"altAnim":false,"mustHitSection":false,"lengthInSteps":16,"typeOfSection":0,"sectionNotes":[[45600,11,0,1,"default"],[45750,9,0,1,"default"],[45900,4,0,1,"default"],[46050,5,0,1,"default"],[46200,7,225,1,"default"],[46500,10,0,1,"default"],[46650,9,0,1,"default"]],"changeTimeScale":false,"timeScale":[4,4],"changeBPM":false,"bpm":180},{"altAnim":false,"mustHitSection":false,"lengthInSteps":16,"typeOfSection":0,"sectionNotes":[[46800,7,225,1,"default"],[47100,9,0,1,"default"],[47250,7,225,1,"default"],[47550,11,0,1,"default"],[47700,8,0,1,"default"],[47850,5,225,1,"default"]],"changeTimeScale":false,"timeScale":[4,4],"changeBPM":false,"bpm":180},{"altAnim":false,"mustHitSection":true,"lengthInSteps":16,"typeOfSection":0,"sectionNotes":[[48000,9,0,0,"default"],[48150,11,0,0,"default"],[48300,10,0,0,"default"],[48450,5,0,0,"default"],[48600,4,0,0,"default"],[48750,9,0,0,"default"],[48900,7,0,0,"default"],[49050,5,0,0,"default"]],"changeTimeScale":false,"timeScale":[4,4],"changeBPM":false,"bpm":180},{"altAnim":false,"mustHitSection":true,"lengthInSteps":16,"typeOfSection":0,"sectionNotes":[[49200,9,0,0,"default"],[49275,6,0,0,"default"],[49350,7,0,0,"default"],[49425,5,0,0,"default"],[49500,10,0,0,"default"],[49650,9,0,0,"default"],[49800,11,0,0,"default"],[49950,7,0,0,"default"],[50100,5,0,0,"default"],[50250,4,0,0,"default"]],"changeTimeScale":false,"timeScale":[4,4],"changeBPM":false,"bpm":180},{"altAnim":false,"mustHitSection":true,"lengthInSteps":16,"typeOfSection":0,"sectionNotes":[[50400,6,0,0,"default"],[50550,7,0,0,"default"],[50700,8,0,0,"default"],[50850,9,0,0,"default"],[51000,11,0,0,"default"],[51150,8,0,0,"default"],[51300,7,0,0,"default"],[51450,5,0,0,"default"]],"changeTimeScale":false,"timeScale":[4,4],"changeBPM":false,"bpm":180},{"altAnim":false,"mustHitSection":true,"lengthInSteps":16,"typeOfSection":0,"sectionNotes":[[51600,4,225,0,"default"],[51900,7,0,0,"default"],[52050,8,0,0,"default"],[52200,10,0,0,"default"],[52275,8,0,0,"default"],[52350,11,0,0,"default"],[52425,9,0,0,"default"],[52500,6,0,0,"default"],[52575,4,0,0,"default"],[52650,7,0,0,"default"],[52725,5,0,0,"default"]],"changeTimeScale":false,"timeScale":[4,4],"changeBPM":false,"bpm":180},{"altAnim":false,"mustHitSection":true,"lengthInSteps":16,"typeOfSection":0,"sectionNotes":[[52800,10,225,1,"default"],[53100,8,0,1,"default"],[53250,5,0,1,"default"],[53400,8,225,1,"default"],[53700,9,225,1,"default"]],"changeTimeScale":false,"timeScale":[4,4],"changeBPM":false,"bpm":180},{"altAnim":false,"mustHitSection":true,"lengthInSteps":16,"typeOfSection":0,"sectionNotes":[[54000,7,0,1,"default"],[54150,6,0,1,"default"],[54300,7,0,1,"default"],[54450,9,0,1,"default"],[54600,4,0,1,"default"],[54900,8,0,1,"default"]],"changeTimeScale":false,"timeScale":[4,4],"changeBPM":false,"bpm":180},{"altAnim":false,"mustHitSection":true,"lengthInSteps":16,"typeOfSection":0,"sectionNotes":[[55200,11,0,1,"default"],[55350,9,0,1,"default"],[55500,4,0,1,"default"],[55650,5,0,1,"default"],[55800,7,225,1,"default"],[56100,10,0,1,"default"],[56250,9,0,1,"default"]],"changeTimeScale":false,"timeScale":[4,4],"changeBPM":false,"bpm":180},{"altAnim":false,"mustHitSection":false,"lengthInSteps":16,"typeOfSection":0,"sectionNotes":[[56400,20,225,0,"default"],[56700,24,0,0,"default"],[56850,26,225,0,"default"]],"changeTimeScale":false,"timeScale":[4,4],"changeBPM":false,"bpm":180},{"altAnim":false,"mustHitSection":false,"lengthInSteps":16,"typeOfSection":0,"sectionNotes":[[57600,15,0,0,"default"],[57750,11,0,0,"default"],[57900,8,0,0,"default"],[58050,11,0,0,"default"],[58350,12,0,0,"default"],[58500,8,0,0,"default"],[58650,15,0,0,"default"],[57600,1,0,1,"default"],[57900,7,0,1,"default"],[58050,5,0,1,"default"],[58350,0,0,1,"default"],[58500,3,0,1,"default"]],"changeTimeScale":false,"timeScale":[4,4],"changeBPM":false,"bpm":180},{"altAnim":false,"mustHitSection":false,"lengthInSteps":16,"typeOfSection":0,"sectionNotes":[[58800,9,0,0,"default"],[59100,12,0,0,"default"],[59400,14,0,0,"default"],[59700,10,0,0,"default"],[59850,13,0,0,"default"],[58800,3,0,1,"default"],[59100,6,0,1,"default"],[59400,4,0,1,"default"],[59700,1,0,1,"default"]],"changeTimeScale":false,"timeScale":[4,4],"changeBPM":false,"bpm":180},{"altAnim":false,"mustHitSection":false,"lengthInSteps":16,"typeOfSection":0,"sectionNotes":[[60000,14,0,0,"default"],[60150,10,0,0,"default"],[60300,9,0,0,"default"],[60450,13,0,0,"default"],[60600,12,0,0,"default"],[60750,8,0,0,"default"],[60900,13,0,0,"default"],[61050,9,0,0,"default"],[60000,0,0,1,"default"],[60300,7,0,1,"default"],[60450,4,0,1,"default"],[60750,3,0,1,"default"],[60900,2,0,1,"default"]],"changeTimeScale":false,"timeScale":[4,4],"changeBPM":false,"bpm":180},{"altAnim":false,"mustHitSection":false,"lengthInSteps":16,"typeOfSection":0,"sectionNotes":[[61200,15,0,0,"default"],[61350,11,0,0,"default"],[61500,10,0,0,"default"],[61650,13,0,0,"default"],[61800,8,0,0,"default"],[61950,12,0,0,"default"],[62100,15,0,0,"default"],[62250,9,0,0,"default"],[61350,6,0,1,"default"],[61500,2,0,1,"default"],[61650,6,0,1,"default"],[61800,7,0,1,"default"],[61950,0,0,1,"default"],[62100,3,0,1,"default"],[62250,5,0,1,"default"]],"changeTimeScale":false,"timeScale":[4,4],"changeBPM":false,"bpm":180},{"altAnim":false,"mustHitSection":false,"lengthInSteps":16,"typeOfSection":0,"sectionNotes":[[62400,15,0,0,"default"],[62550,11,0,0,"default"],[62700,8,0,0,"default"],[62850,10,0,0,"default"],[63000,12,225,0,"default"],[63300,15,0,0,"default"],[63450,12,0,0,"default"],[62400,1,0,1,"default"],[62700,4,0,1,"default"],[62850,1,0,1,"default"],[63150,0,0,1,"default"],[63300,5,0,1,"default"]],"changeTimeScale":false,"timeScale":[4,4],"changeBPM":false,"bpm":180},{"altAnim":false,"mustHitSection":false,"lengthInSteps":16,"typeOfSection":0,"sectionNotes":[[63600,14,0,0,"default"],[63750,12,0,0,"default"],[63900,11,0,0,"default"],[64050,9,0,0,"default"],[64200,10,0,0,"default"],[64275,8,0,0,"default"],[64350,11,0,0,"default"],[64425,9,0,0,"default"],[64500,14,0,0,"default"],[64575,12,0,0,"default"],[64725,13,0,0,"default"],[64650,15,0,0,"default"],[63600,1,0,1,"default"],[63900,6,0,1,"default"],[64200,7,0,1,"default"],[64500,0,0,1,"default"]],"changeTimeScale":false,"timeScale":[4,4],"changeBPM":false,"bpm":180},{"altAnim":false,"mustHitSection":false,"lengthInSteps":16,"typeOfSection":0,"sectionNotes":[[64800,11,0,0,"default"],[65100,13,0,0,"default"],[65250,10,0,0,"default"],[65550,14,0,0,"default"],[65700,9,0,0,"default"],[64800,7,0,1,"default"],[65100,0,0,1,"default"],[65250,3,0,1,"default"],[65550,4,0,1,"default"],[65700,6,0,1,"default"]],"changeTimeScale":false,"timeScale":[4,4],"changeBPM":false,"bpm":180},{"altAnim":false,"mustHitSection":false,"lengthInSteps":16,"typeOfSection":0,"sectionNotes":[[66000,13,0,0,"default"],[66150,10,0,0,"default"],[66450,14,0,0,"default"],[66600,9,0,0,"default"],[66900,8,0,0,"default"],[66150,7,0,1,"default"],[66300,3,0,1,"default"],[66450,7,0,1,"default"],[66600,6,0,1,"default"],[66750,4,0,1,"default"],[66900,2,0,1,"default"],[67050,1,0,1,"default"]],"changeTimeScale":false,"timeScale":[4,4],"changeBPM":false,"bpm":180},{"altAnim":false,"mustHitSection":false,"lengthInSteps":16,"typeOfSection":0,"sectionNotes":[[67500,8,0,0,"default"],[67800,9,0,0,"default"],[67200,14,0,0,"default"],[68100,10,0,0,"default"],[68250,11,0,0,"default"],[67200,0,0,1,"default"],[67500,4,0,1,"default"],[67575,0,0,1,"default"],[67650,4,0,1,"default"],[67800,7,0,1,"default"],[68100,3,0,1,"default"]],"changeTimeScale":false,"timeScale":[4,4],"changeBPM":false,"bpm":180},{"altAnim":false,"mustHitSection":false,"lengthInSteps":16,"typeOfSection":0,"sectionNotes":[[68400,13,0,0,"default"],[68700,14,0,0,"default"],[69000,8,0,0,"default"],[69300,9,0,0,"default"],[68400,6,0,1,"default"],[68550,0,0,1,"default"],[68700,3,0,1,"default"],[68850,5,0,1,"default"],[69000,6,0,1,"default"],[69150,0,0,1,"default"],[69300,3,0,1,"default"],[69450,1,0,1,"default"]],"changeTimeScale":false,"timeScale":[4,4],"changeBPM":false,"bpm":180},{"altAnim":false,"mustHitSection":false,"lengthInSteps":16,"typeOfSection":0,"sectionNotes":[[69600,15,0,0,"default"],[69675,14,0,0,"default"],[69750,13,0,0,"default"],[69825,15,0,0,"default"],[69900,14,0,0,"default"],[69975,13,0,0,"default"],[70050,12,0,0,"default"],[70125,13,0,0,"default"],[70200,8,0,0,"default"],[70275,9,0,0,"default"],[70350,10,0,0,"default"],[70425,8,0,0,"default"],[70500,9,0,0,"default"],[70575,10,0,0,"default"],[70650,11,0,0,"default"],[70725,10,0,0,"default"],[69600,1,0,1,"default"],[69900,6,0,1,"default"],[70050,4,0,1,"default"],[70500,3,0,1,"default"],[70350,5,0,1,"default"],[70650,2,0,1,"default"]],"changeTimeScale":false,"timeScale":[4,4],"changeBPM":false,"bpm":180},{"altAnim":false,"mustHitSection":false,"lengthInSteps":16,"typeOfSection":0,"sectionNotes":[[70800,14,0,0,"default"],[70950,15,0,0,"default"],[71100,12,0,0,"default"],[71250,10,0,0,"default"],[71400,11,225,0,"default"],[71700,9,0,0,"default"],[70950,6,0,1,"default"],[71100,4,0,1,"default"],[71250,1,0,1,"default"],[71400,2,225,1,"default"],[71700,7,0,1,"default"]],"changeTimeScale":false,"timeScale":[4,4],"changeBPM":false,"bpm":180},{"altAnim":false,"mustHitSection":false,"lengthInSteps":16,"typeOfSection":0,"sectionNotes":[[72000,15,0,0,"default"],[72075,14,0,0,"default"],[72150,13,0,0,"default"],[72225,15,0,0,"default"],[72300,14,0,0,"default"],[72375,13,0,0,"default"],[72450,12,0,0,"default"],[72525,13,0,0,"default"],[72600,8,0,0,"default"],[72675,9,0,0,"default"],[72750,10,0,0,"default"],[72825,8,0,0,"default"],[72900,9,0,0,"default"],[72975,10,0,0,"default"],[73050,11,0,0,"default"],[73125,10,0,0,"default"],[72000,0,375,1,"default"],[72450,5,375,1,"default"],[72900,4,0,1,"default"],[73050,7,0,1,"default"]],"changeTimeScale":false,"timeScale":[4,4],"changeBPM":false,"bpm":180},{"altAnim":false,"mustHitSection":false,"lengthInSteps":16,"typeOfSection":0,"sectionNotes":[[73200,13,0,0,"default"],[73275,15,0,0,"default"],[73350,12,0,0,"default"],[73425,13,0,0,"default"],[73500,15,0,0,"default"],[73575,12,0,0,"default"],[73650,13,0,0,"default"],[73725,15,0,0,"default"],[73800,10,0,0,"default"],[73875,8,0,0,"default"],[73950,11,0,0,"default"],[74025,10,0,0,"default"],[74100,8,0,0,"default"],[74175,11,0,0,"default"],[74250,10,0,0,"default"],[74325,8,0,0,"default"],[73200,6,225,1,"default"],[73500,0,225,1,"default"],[73800,5,225,1,"default"],[74100,4,225,1,"default"]],"changeTimeScale":false,"timeScale":[4,4],"changeBPM":false,"bpm":180},{"altAnim":false,"mustHitSection":false,"lengthInSteps":16,"typeOfSection":0,"sectionNotes":[[74400,14,0,0,"default"],[74700,10,0,0,"default"],[75000,8,0,0,"default"],[75300,14,0,0,"default"],[74400,6,0,1,"default"],[74700,2,0,1,"default"],[75000,0,0,1,"default"],[75300,6,0,1,"default"]],"changeTimeScale":false,"timeScale":[4,4],"changeBPM":false,"bpm":180},{"altAnim":false,"mustHitSection":false,"lengthInSteps":16,"typeOfSection":0,"sectionNotes":[[75600,9,0,0,"default"],[75900,13,0,0,"default"],[76200,14,0,0,"default"],[76500,8,0,0,"default"],[76650,10,0,0,"default"],[75600,7,0,1,"default"],[75900,0,0,1,"default"],[76200,7,0,1,"default"],[76350,0,0,1,"default"],[76500,7,0,1,"default"],[76575,4,0,1,"default"],[76650,3,0,1,"default"],[76725,0,0,1,"default"]],"changeTimeScale":false,"timeScale":[4,4],"changeBPM":false,"bpm":180},{"altAnim":false,"mustHitSection":true,"lengthInSteps":16,"typeOfSection":0,"sectionNotes":[[76800,15,0,0,"default"],[76950,11,0,0,"default"],[77100,8,0,0,"default"],[77250,11,0,0,"default"],[77550,12,0,0,"default"],[77700,8,0,0,"default"],[77850,15,0,0,"default"],[76800,1,0,1,"default"],[77100,7,0,1,"default"],[77250,5,0,1,"default"],[77550,0,0,1,"default"],[77700,3,0,1,"default"]],"changeTimeScale":false,"timeScale":[4,4],"changeBPM":false,"bpm":180},{"altAnim":false,"mustHitSection":true,"lengthInSteps":16,"typeOfSection":0,"sectionNotes":[[78000,9,0,0,"default"],[78300,12,0,0,"default"],[78600,14,0,0,"default"],[78900,10,0,0,"default"],[79050,13,0,0,"default"],[78000,3,0,1,"default"],[78300,6,0,1,"default"],[78600,4,0,1,"default"],[78900,1,0,1,"default"]],"changeTimeScale":false,"timeScale":[4,4],"changeBPM":false,"bpm":180},{"altAnim":false,"mustHitSection":true,"lengthInSteps":16,"typeOfSection":0,"sectionNotes":[[79200,14,0,0,"default"],[79350,10,0,0,"default"],[79500,9,0,0,"default"],[79650,13,0,0,"default"],[79800,12,0,0,"default"],[79950,8,0,0,"default"],[80100,13,0,0,"default"],[80250,9,0,0,"default"],[79200,0,0,1,"default"],[79500,7,0,1,"default"],[79650,4,0,1,"default"],[79950,3,0,1,"default"],[80100,2,0,1,"default"]],"changeTimeScale":false,"timeScale":[4,4],"changeBPM":false,"bpm":180},{"altAnim":false,"mustHitSection":true,"lengthInSteps":16,"typeOfSection":0,"sectionNotes":[[80400,15,0,0,"default"],[80550,11,0,0,"default"],[80700,10,0,0,"default"],[80850,13,0,0,"default"],[81000,8,0,0,"default"],[81150,12,0,0,"default"],[81300,15,0,0,"default"],[81450,9,0,0,"default"],[80550,6,0,1,"default"],[80700,2,0,1,"default"],[80850,6,0,1,"default"],[81000,7,0,1,"default"],[81150,0,0,1,"default"],[81300,3,0,1,"default"],[81450,5,0,1,"default"]],"changeTimeScale":false,"timeScale":[4,4],"changeBPM":false,"bpm":180},{"altAnim":false,"mustHitSection":true,"lengthInSteps":16,"typeOfSection":0,"sectionNotes":[[81600,15,0,0,"default"],[81750,11,0,0,"default"],[81900,8,0,0,"default"],[82050,10,0,0,"default"],[82200,12,225,0,"default"],[82500,15,0,0,"default"],[82650,12,0,0,"default"],[81600,1,0,1,"default"],[81900,4,0,1,"default"],[82050,1,0,1,"default"],[82350,0,0,1,"default"],[82500,5,0,1,"default"]],"changeTimeScale":false,"timeScale":[4,4],"changeBPM":false,"bpm":180},{"altAnim":false,"mustHitSection":true,"lengthInSteps":16,"typeOfSection":0,"sectionNotes":[[82800,14,0,0,"default"],[82950,12,0,0,"default"],[83100,11,0,0,"default"],[83250,9,0,0,"default"],[83400,10,0,0,"default"],[83475,8,0,0,"default"],[83550,11,0,0,"default"],[83625,9,0,0,"default"],[83700,14,0,0,"default"],[83775,12,0,0,"default"],[83925,13,0,0,"default"],[83850,15,0,0,"default"],[82800,1,0,1,"default"],[83100,6,0,1,"default"],[83400,7,0,1,"default"],[83700,0,0,1,"default"]],"changeTimeScale":false,"timeScale":[4,4],"changeBPM":false,"bpm":180},{"altAnim":false,"mustHitSection":true,"lengthInSteps":16,"typeOfSection":0,"sectionNotes":[[84000,11,0,0,"default"],[84300,13,0,0,"default"],[84450,10,0,0,"default"],[84750,14,0,0,"default"],[84900,9,0,0,"default"],[84000,7,0,1,"default"],[84300,0,0,1,"default"],[84450,3,0,1,"default"],[84750,4,0,1,"default"],[84900,6,0,1,"default"]],"changeTimeScale":false,"timeScale":[4,4],"changeBPM":false,"bpm":180},{"altAnim":false,"mustHitSection":true,"lengthInSteps":16,"typeOfSection":0,"sectionNotes":[[85200,13,0,0,"default"],[85350,10,0,0,"default"],[85650,14,0,0,"default"],[85800,9,0,0,"default"],[86100,8,0,0,"default"],[85350,7,0,1,"default"],[85500,3,0,1,"default"],[85650,7,0,1,"default"],[85800,6,0,1,"default"],[85950,4,0,1,"default"],[86100,2,0,1,"default"],[86250,1,0,1,"default"]],"changeTimeScale":false,"timeScale":[4,4],"changeBPM":false,"bpm":180},{"altAnim":false,"mustHitSection":true,"lengthInSteps":16,"typeOfSection":0,"sectionNotes":[[86700,8,0,0,"default"],[87000,9,0,0,"default"],[86400,14,0,0,"default"],[87300,10,0,0,"default"],[87450,11,0,0,"default"],[86400,0,0,1,"default"],[86700,4,0,1,"default"],[86775,0,0,1,"default"],[86850,4,0,1,"default"],[87000,7,0,1,"default"],[87300,3,0,1,"default"]],"changeTimeScale":false,"timeScale":[4,4],"changeBPM":false,"bpm":180},{"altAnim":false,"mustHitSection":true,"lengthInSteps":16,"typeOfSection":0,"sectionNotes":[[87600,13,0,0,"default"],[87900,14,0,0,"default"],[88200,8,0,0,"default"],[88500,9,0,0,"default"],[87600,6,0,1,"default"],[87750,0,0,1,"default"],[87900,3,0,1,"default"],[88050,5,0,1,"default"],[88200,6,0,1,"default"],[88350,0,0,1,"default"],[88500,3,0,1,"default"],[88650,1,0,1,"default"]],"changeTimeScale":false,"timeScale":[4,4],"changeBPM":false,"bpm":180},{"altAnim":false,"mustHitSection":true,"lengthInSteps":16,"typeOfSection":0,"sectionNotes":[[88800,15,0,0,"default"],[88875,14,0,0,"default"],[88950,13,0,0,"default"],[89025,15,0,0,"default"],[89100,14,0,0,"default"],[89175,13,0,0,"default"],[89250,12,0,0,"default"],[89325,13,0,0,"default"],[89400,8,0,0,"default"],[89475,9,0,0,"default"],[89550,10,0,0,"default"],[89625,8,0,0,"default"],[89700,9,0,0,"default"],[89775,10,0,0,"default"],[89850,11,0,0,"default"],[89925,10,0,0,"default"],[88800,1,0,1,"default"],[89100,6,0,1,"default"],[89250,4,0,1,"default"],[89700,3,0,1,"default"],[89550,5,0,1,"default"],[89850,2,0,1,"default"]],"changeTimeScale":false,"timeScale":[4,4],"changeBPM":false,"bpm":180},{"altAnim":false,"mustHitSection":true,"lengthInSteps":16,"typeOfSection":0,"sectionNotes":[[90000,14,0,0,"default"],[90150,15,0,0,"default"],[90300,12,0,0,"default"],[90450,10,0,0,"default"],[90600,11,225,0,"default"],[90900,9,0,0,"default"],[90150,6,0,1,"default"],[90300,4,0,1,"default"],[90450,1,0,1,"default"],[90600,2,225,1,"default"],[90900,7,0,1,"default"]],"changeTimeScale":false,"timeScale":[4,4],"changeBPM":false,"bpm":180},{"altAnim":false,"mustHitSection":true,"lengthInSteps":16,"typeOfSection":0,"sectionNotes":[[91200,15,0,0,"default"],[91275,14,0,0,"default"],[91350,13,0,0,"default"],[91425,15,0,0,"default"],[91500,14,0,0,"default"],[91575,13,0,0,"default"],[91650,12,0,0,"default"],[91725,13,0,0,"default"],[91800,8,0,0,"default"],[91875,9,0,0,"default"],[91950,10,0,0,"default"],[92025,8,0,0,"default"],[92100,9,0,0,"default"],[92175,10,0,0,"default"],[92250,11,0,0,"default"],[92325,10,0,0,"default"],[91200,0,375,1,"default"],[91650,5,375,1,"default"],[92100,4,0,1,"default"],[92250,7,0,1,"default"]],"changeTimeScale":false,"timeScale":[4,4],"changeBPM":false,"bpm":180},{"altAnim":false,"mustHitSection":true,"lengthInSteps":16,"typeOfSection":0,"sectionNotes":[[92400,13,0,0,"default"],[92475,15,0,0,"default"],[92550,12,0,0,"default"],[92625,13,0,0,"default"],[92700,15,0,0,"default"],[92775,12,0,0,"default"],[92850,13,0,0,"default"],[92925,15,0,0,"default"],[93000,10,0,0,"default"],[93075,8,0,0,"default"],[93150,11,0,0,"default"],[93225,10,0,0,"default"],[93300,8,0,0,"default"],[93375,11,0,0,"default"],[93450,10,0,0,"default"],[93525,8,0,0,"default"],[92400,6,225,1,"default"],[92700,0,225,1,"default"],[93000,5,225,1,"default"],[93300,4,225,1,"default"]],"changeTimeScale":false,"timeScale":[4,4],"changeBPM":false,"bpm":180},{"altAnim":false,"mustHitSection":true,"lengthInSteps":16,"typeOfSection":0,"sectionNotes":[[93600,14,0,0,"default"],[93900,10,0,0,"default"],[94200,8,0,0,"default"],[94500,14,0,0,"default"],[93600,6,0,1,"default"],[93900,2,0,1,"default"],[94200,0,0,1,"default"],[94500,6,0,1,"default"]],"changeTimeScale":false,"timeScale":[4,4],"bpm":180,"changeBPM":false},{"altAnim":false,"mustHitSection":true,"lengthInSteps":16,"typeOfSection":0,"sectionNotes":[[94800,9,0,0,"default"],[95100,13,0,0,"default"],[95400,14,0,0,"default"],[95700,8,0,0,"default"],[95850,10,0,0,"default"],[94800,7,0,1,"default"],[95100,0,0,1,"default"],[95400,7,0,1,"default"],[95550,0,0,1,"default"],[95700,7,0,1,"default"],[95775,4,0,1,"default"],[95850,3,0,1,"default"],[95925,0,0,1,"default"]],"changeTimeScale":false,"timeScale":[4,4],"bpm":180,"changeBPM":false},{"altAnim":false,"mustHitSection":false,"lengthInSteps":16,"typeOfSection":0,"sectionNotes":[[96000,18,450,1,"default"],[96000,1,0,0,"default"],[96150,3,0,0,"default"],[96300,8,0,0,"default"],[96450,14,0,0,"default"],[96750,10,0,0,"default"],[96900,4,0,0,"default"],[97050,5,0,0,"default"]],"changeTimeScale":false,"timeScale":[4,4],"changeBPM":false,"bpm":180},{"altAnim":false,"mustHitSection":false,"lengthInSteps":16,"typeOfSection":0,"sectionNotes":[[97350,5,0,0,"default"],[97500,14,0,0,"default"],[97650,13,0,0,"default"],[97800,15,0,0,"default"],[98100,8,0,0,"default"],[98175,9,0,0,"default"],[98250,6,0,0,"default"]],"changeTimeScale":false,"timeScale":[4,4],"changeBPM":false,"bpm":200},{"altAnim":false,"mustHitSection":false,"lengthInSteps":16,"typeOfSection":0,"sectionNotes":[[98400,3,0,0,"default"],[98850,8,0,0,"default"],[99300,9,0,0,"default"]],"changeTimeScale":false,"timeScale":[4,4],"changeBPM":false,"bpm":200},{"altAnim":false,"mustHitSection":false,"lengthInSteps":16,"typeOfSection":0,"sectionNotes":[[99600,1,0,0,"default"],[99900,5,0,0,"default"],[100050,13,0,0,"default"],[100125,9,0,0,"default"],[100200,7,0,0,"default"],[100500,4,225,0,"default"]],"changeTimeScale":false,"timeScale":[4,4],"changeBPM":false,"bpm":200},{"altAnim":false,"mustHitSection":false,"lengthInSteps":16,"typeOfSection":0,"sectionNotes":[[100800,5,0,1,"default"],[100950,10,0,1,"default"],[101100,11,0,1,"default"],[101250,0,0,1,"default"],[101550,6,0,1,"default"],[101700,7,0,1,"default"],[101850,13,0,1,"default"]],"changeTimeScale":false,"timeScale":[4,4],"changeBPM":false,"bpm":200},{"altAnim":false,"mustHitSection":false,"lengthInSteps":16,"typeOfSection":0,"sectionNotes":[[102150,13,0,1,"default"],[102300,12,0,1,"default"],[102450,15,0,1,"default"],[102600,9,0,1,"default"],[102750,5,0,1,"default"],[102900,0,0,1,"default"],[102975,1,0,1,"default"],[103050,3,0,1,"default"]],"changeTimeScale":false,"timeScale":[4,4],"changeBPM":false,"bpm":200},{"altAnim":false,"mustHitSection":false,"lengthInSteps":16,"typeOfSection":0,"sectionNotes":[[103200,10,0,1,"default"],[103650,11,0,1,"default"],[104100,5,0,1,"default"]],"changeTimeScale":false,"timeScale":[4,4],"changeBPM":false,"bpm":200},{"altAnim":false,"mustHitSection":false,"lengthInSteps":16,"typeOfSection":0,"sectionNotes":[[104400,0,0,1,"default"],[104700,4,0,1,"default"],[104850,12,0,1,"default"],[104925,8,0,1,"default"],[105000,7,0,1,"default"],[105300,9,0,1,"default"]],"changeTimeScale":false,"timeScale":[4,4],"bpm":200,"changeBPM":false},{"altAnim":false,"mustHitSection":true,"lengthInSteps":16,"typeOfSection":0,"sectionNotes":[[105600,1,0,0,"default"],[105750,3,0,0,"default"],[105900,8,0,0,"default"],[106050,14,0,0,"default"],[106350,10,0,0,"default"],[106500,4,0,0,"default"],[106650,5,0,0,"default"],[105750,27,0,0,"default"],[105900,24,0,0,"default"],[106200,17,0,0,"default"],[106500,24,0,0,"default"],[106650,26,0,0,"default"],[105600,26,0,1,"default"]],"changeTimeScale":false,"timeScale":[4,4],"bpm":200,"changeBPM":false},{"altAnim":false,"mustHitSection":true,"lengthInSteps":16,"typeOfSection":0,"sectionNotes":[[106950,5,0,0,"default"],[107100,14,0,0,"default"],[107250,13,0,0,"default"],[107400,15,0,0,"default"],[107700,8,0,0,"default"],[107775,9,0,0,"default"],[107850,6,0,0,"default"],[106950,21,0,0,"default"],[107100,20,0,0,"default"],[107400,31,0,0,"default"],[107700,30,0,0,"default"],[107850,28,0,0,"default"]],"changeTimeScale":false,"timeScale":[4,4],"bpm":200,"changeBPM":false},{"altAnim":false,"mustHitSection":true,"lengthInSteps":16,"typeOfSection":0,"sectionNotes":[[108000,3,0,0,"default"],[108450,8,0,0,"default"],[108900,9,0,0,"default"],[108150,27,0,0,"default"],[108300,24,0,0,"default"],[108600,17,0,0,"default"],[108900,27,0,0,"default"],[109050,28,0,0,"default"]],"changeTimeScale":false,"timeScale":[4,4],"changeBPM":false,"bpm":200},{"altAnim":false,"mustHitSection":true,"lengthInSteps":16,"typeOfSection":0,"sectionNotes":[[109200,1,0,0,"default"],[109500,5,0,0,"default"],[109650,13,0,0,"default"],[109725,9,0,0,"default"],[109800,7,0,0,"default"],[110100,4,225,0,"default"],[109350,26,0,0,"default"],[109500,24,0,0,"default"],[109800,30,0,0,"default"],[109875,28,0,0,"default"],[109950,27,0,0,"default"],[110025,25,0,0,"default"],[110100,18,0,0,"default"],[110175,19,0,0,"default"],[110250,20,0,0,"default"],[110325,21,0,0,"default"]],"changeTimeScale":false,"timeScale":[4,4],"changeBPM":false,"bpm":200},{"altAnim":false,"mustHitSection":true,"lengthInSteps":16,"typeOfSection":0,"sectionNotes":[[110400,5,0,1,"default"],[110550,10,0,1,"default"],[110700,11,0,1,"default"],[110850,0,0,1,"default"],[111150,6,0,1,"default"],[111300,7,0,1,"default"],[111450,13,0,1,"default"],[110550,26,0,0,"default"],[110700,28,0,0,"default"],[111000,21,0,0,"default"],[111300,20,0,0,"default"],[111450,19,0,0,"default"]],"changeTimeScale":false,"timeScale":[4,4],"changeBPM":false,"bpm":200},{"altAnim":false,"mustHitSection":true,"lengthInSteps":16,"typeOfSection":0,"sectionNotes":[[111750,13,0,1,"default"],[111900,12,0,1,"default"],[112050,15,0,1,"default"],[112200,9,0,1,"default"],[112350,5,0,1,"default"],[112500,0,0,1,"default"],[112575,1,0,1,"default"],[112650,3,0,1,"default"],[111750,25,0,0,"default"],[111900,19,0,0,"default"],[112200,23,0,0,"default"],[112500,22,0,0,"default"],[112650,20,0,0,"default"]],"changeTimeScale":false,"timeScale":[4,4],"changeBPM":false,"bpm":200},{"altAnim":false,"mustHitSection":true,"lengthInSteps":16,"typeOfSection":0,"sectionNotes":[[112800,10,0,1,"default"],[113250,11,0,1,"default"],[113700,5,0,1,"default"],[112950,26,0,0,"default"],[113100,28,0,0,"default"],[113400,29,0,0,"default"],[113700,18,0,0,"default"],[113850,19,0,0,"default"]],"changeTimeScale":false,"timeScale":[4,4],"changeBPM":false,"bpm":200},{"altAnim":false,"mustHitSection":true,"lengthInSteps":16,"typeOfSection":0,"sectionNotes":[[114000,0,0,1,"default"],[114300,4,0,1,"default"],[114450,12,0,1,"default"],[114525,8,0,1,"default"],[114600,7,0,1,"default"],[114900,9,0,1,"default"],[114150,24,0,0,"default"],[114300,23,0,0,"default"],[114525,30,0,0,"default"],[114600,28,0,0,"default"],[114675,26,0,0,"default"],[114750,25,0,0,"default"],[114825,18,0,0,"default"],[114900,19,0,0,"default"],[114975,22,0,0,"default"],[115050,21,0,0,"default"]],"changeTimeScale":false,"timeScale":[4,4],"changeBPM":false,"bpm":200},{"altAnim":false,"mustHitSection":true,"lengthInSteps":16,"typeOfSection":0,"sectionNotes":[[115200,10,600,1,"default"],[116100,18,0,0,"default"]],"changeTimeScale":false,"timeScale":[4,4],"changeBPM":false,"bpm":200},{"altAnim":false,"mustHitSection":false,"lengthInSteps":16,"typeOfSection":0,"sectionNotes":[[116400,11,0,0,"default"],[117000,5,0,0,"default"]],"changeTimeScale":false,"timeScale":[4,4],"changeBPM":false,"bpm":200},{"altAnim":false,"mustHitSection":false,"lengthInSteps":16,"typeOfSection":0,"sectionNotes":[[117600,3,0,0,"default"],[117900,4,0,0,"default"],[118050,6,0,0,"default"],[118200,11,0,0,"default"],[118425,9,0,0,"default"],[118500,8,0,0,"default"],[118650,10,0,0,"default"]],"changeTimeScale":false,"timeScale":[4,4],"changeBPM":false,"bpm":200},{"altAnim":false,"mustHitSection":false,"lengthInSteps":16,"typeOfSection":0,"sectionNotes":[[119400,13,0,0,"default"],[118875,8,0,0,"default"],[119025,6,0,0,"default"]],"changeTimeScale":false,"timeScale":[4,4],"changeBPM":false,"bpm":200},{"altAnim":false,"mustHitSection":false,"lengthInSteps":16,"typeOfSection":0,"sectionNotes":[[120900,22,225,0,"default"]],"changeTimeScale":false,"timeScale":[4,4],"changeBPM":false,"bpm":200},{"altAnim":false,"mustHitSection":true,"lengthInSteps":16,"typeOfSection":0,"sectionNotes":[[121200,11,225,0,"default"],[121800,5,225,0,"default"]],"changeTimeScale":false,"timeScale":[4,4],"changeBPM":false,"bpm":200},{"altAnim":false,"mustHitSection":true,"lengthInSteps":16,"typeOfSection":0,"sectionNotes":[[122850,0,0,0,"default"],[123150,3,0,0,"default"],[122400,10,0,0,"default"],[122550,10,0,0,"default"],[123450,5,0,0,"default"]],"changeTimeScale":false,"timeScale":[4,4],"changeBPM":false,"bpm":200},{"altAnim":false,"mustHitSection":true,"lengthInSteps":16,"typeOfSection":0,"sectionNotes":[[123600,7,0,0,"default"],[123750,7,0,0,"default"],[123900,5,0,0,"default"],[124200,11,0,0,"default"],[124350,8,0,0,"default"],[124650,13,0,0,"default"]],"changeTimeScale":false,"timeScale":[4,4],"changeBPM":false,"bpm":200},{"altAnim":false,"mustHitSection":true,"lengthInSteps":16,"typeOfSection":0,"sectionNotes":[[124800,10,675,0,"default"]],"changeTimeScale":false,"timeScale":[4,4],"changeBPM":false,"bpm":200},{"altAnim":false,"mustHitSection":true,"lengthInSteps":16,"typeOfSection":0,"sectionNotes":[],"changeTimeScale":false,"timeScale":[4,4],"changeBPM":false,"bpm":200},{"altAnim":false,"mustHitSection":false,"lengthInSteps":16,"typeOfSection":0,"sectionNotes":[],"changeTimeScale":false,"timeScale":[4,4],"changeBPM":false,"bpm":200},{"altAnim":false,"mustHitSection":true,"lengthInSteps":16,"typeOfSection":0,"sectionNotes":[],"changeTimeScale":false,"timeScale":[4,4],"changeBPM":false,"bpm":200},{"altAnim":false,"mustHitSection":true,"lengthInSteps":16,"typeOfSection":0,"sectionNotes":[[129600,10,375,0,"default"],[130050,4,0,0,"default"],[130500,5,225,0,"default"]],"changeTimeScale":false,"timeScale":[4,4],"changeBPM":false,"bpm":200},{"altAnim":false,"mustHitSection":true,"lengthInSteps":16,"typeOfSection":0,"sectionNotes":[[130800,3,375,0,"default"],[131250,12,0,0,"default"],[131700,9,225,0,"default"]],"changeTimeScale":false,"timeScale":[4,4],"changeBPM":false,"bpm":200},{"altAnim":false,"mustHitSection":true,"lengthInSteps":16,"typeOfSection":0,"sectionNotes":[[132000,11,0,0,"default"],[132150,11,0,0,"default"],[132300,9,0,0,"default"],[132450,7,0,0,"default"],[132600,7,0,0,"default"],[132750,5,0,0,"default"],[132900,6,0,0,"default"],[133050,5,0,0,"default"]],"changeTimeScale":false,"timeScale":[4,4],"changeBPM":false,"bpm":200},{"altAnim":false,"mustHitSection":true,"lengthInSteps":16,"typeOfSection":0,"sectionNotes":[[133200,4,525,0,"default"],[133800,7,225,0,"default"],[134100,5,225,0,"default"]],"changeTimeScale":false,"timeScale":[4,4],"changeBPM":false,"bpm":200},{"altAnim":false,"mustHitSection":false,"lengthInSteps":16,"typeOfSection":0,"sectionNotes":[[134700,4,0,0,"default"],[134850,13,0,0,"default"],[135150,10,0,0,"default"],[135300,11,0,0,"default"],[135450,1,0,0,"default"],[135525,4,0,0,"default"],[134400,7,0,0,"default"],[134550,11,0,0,"default"]],"changeTimeScale":false,"timeScale":[4,4],"changeBPM":false,"bpm":200},{"altAnim":false,"mustHitSection":false,"lengthInSteps":16,"typeOfSection":0,"sectionNotes":[[135600,11,0,0,"default"],[135675,13,0,0,"default"],[135750,3,0,0,"default"],[135825,5,0,0,"default"],[135900,2,0,0,"default"],[135975,8,0,0,"default"],[136050,11,0,0,"default"],[136200,9,0,0,"default"],[136350,9,0,0,"default"],[136500,3,0,0,"default"],[136650,12,0,0,"default"]],"changeTimeScale":false,"timeScale":[4,4],"changeBPM":false,"bpm":200},{"altAnim":false,"mustHitSection":false,"lengthInSteps":16,"typeOfSection":0,"sectionNotes":[[137250,13,0,0,"default"],[137550,10,0,0,"default"],[137700,11,0,0,"default"],[137850,1,0,0,"default"],[137925,4,0,0,"default"],[136800,7,0,0,"default"],[136950,11,0,0,"default"],[137100,2,0,0,"default"]],"changeTimeScale":false,"timeScale":[4,4],"bpm":200,"changeBPM":false},{"altAnim":false,"mustHitSection":false,"lengthInSteps":16,"typeOfSection":0,"sectionNotes":[[138000,11,0,0,"default"],[138075,13,0,0,"default"],[138150,3,0,0,"default"],[138225,5,0,0,"default"],[138300,2,0,0,"default"],[138375,8,0,0,"default"],[138450,11,0,0,"default"],[138600,9,0,0,"default"],[138750,9,0,0,"default"],[138900,3,0,0,"default"],[139050,12,0,0,"default"]],"changeTimeScale":false,"timeScale":[4,4],"bpm":200,"changeBPM":false},{"altAnim":false,"mustHitSection":true,"lengthInSteps":16,"typeOfSection":0,"sectionNotes":[[139500,4,0,0,"default"],[139650,13,0,0,"default"],[139950,10,0,0,"default"],[140100,11,0,0,"default"],[140250,1,0,0,"default"],[140325,4,0,0,"default"],[139200,7,0,0,"default"],[139350,11,0,0,"default"]],"changeTimeScale":false,"timeScale":[4,4],"bpm":200,"changeBPM":false},{"altAnim":false,"mustHitSection":true,"lengthInSteps":16,"typeOfSection":0,"sectionNotes":[[140400,11,0,0,"default"],[140475,13,0,0,"default"],[140550,3,0,0,"default"],[140625,5,0,0,"default"],[140700,2,0,0,"default"],[140775,8,0,0,"default"],[140850,11,0,0,"default"],[141000,9,0,0,"default"],[141150,9,0,0,"default"],[141300,3,0,0,"default"],[141450,12,0,0,"default"]],"changeTimeScale":false,"timeScale":[4,4],"bpm":200,"changeBPM":false},{"altAnim":false,"mustHitSection":true,"lengthInSteps":16,"typeOfSection":0,"sectionNotes":[[142050,13,0,0,"default"],[142350,10,0,0,"default"],[142500,11,0,0,"default"],[142650,1,0,0,"default"],[142725,4,0,0,"default"],[141600,7,0,0,"default"],[141750,11,0,0,"default"],[141900,2,0,0,"default"]],"changeTimeScale":false,"timeScale":[4,4],"bpm":200,"changeBPM":false},{"altAnim":false,"mustHitSection":true,"lengthInSteps":16,"typeOfSection":0,"sectionNotes":[[142800,11,0,0,"default"],[142875,13,0,0,"default"],[142950,3,0,0,"default"],[143025,5,0,0,"default"],[143100,2,0,0,"default"],[143175,8,0,0,"default"],[143250,11,0,0,"default"],[143400,9,0,0,"default"],[143550,9,0,0,"default"],[143700,3,0,0,"default"],[143850,12,0,0,"default"]],"changeTimeScale":false,"timeScale":[4,4],"bpm":200,"changeBPM":false},{"altAnim":false,"mustHitSection":false,"lengthInSteps":16,"typeOfSection":0,"sectionNotes":[[144300,4,0,1,"default"],[144450,13,0,1,"default"],[144750,10,0,1,"default"],[144900,11,0,1,"default"],[145050,1,0,1,"default"],[145125,4,0,1,"default"],[144000,5,0,1,"default"],[144150,11,0,1,"default"],[144075,8,0,1,"default"],[144225,9,0,1,"default"],[144375,6,0,1,"default"],[144975,8,0,1,"default"]],"changeTimeScale":false,"timeScale":[4,4],"bpm":200,"changeBPM":false},{"altAnim":false,"mustHitSection":false,"lengthInSteps":16,"typeOfSection":0,"sectionNotes":[[145200,11,0,1,"default"],[145275,13,0,1,"default"],[145350,3,0,1,"default"],[145425,5,0,1,"default"],[145500,2,0,1,"default"],[145575,8,0,1,"default"],[145650,11,0,1,"default"],[145800,9,0,1,"default"],[145950,9,0,1,"default"],[146100,3,0,1,"default"],[146250,12,0,1,"default"]],"changeTimeScale":false,"timeScale":[4,4],"bpm":200,"changeBPM":false},{"altAnim":false,"mustHitSection":false,"lengthInSteps":16,"typeOfSection":0,"sectionNotes":[[146475,9,0,1,"default"],[146550,14,0,1,"default"],[146625,10,0,1,"default"],[146775,8,0,1,"default"],[147375,7,0,1,"default"],[146400,5,0,1,"default"],[146700,4,0,1,"default"],[147150,10,0,1,"default"],[147300,11,0,1,"default"],[147525,4,0,1,"default"],[147450,1,0,1,"default"],[146850,13,0,1,"default"]],"changeTimeScale":false,"timeScale":[4,4],"bpm":200,"changeBPM":false},{"altAnim":false,"mustHitSection":false,"lengthInSteps":16,"typeOfSection":0,"sectionNotes":[[148575,5,0,1,"default"],[148725,10,0,1,"default"],[147600,11,0,1,"default"],[147675,13,0,1,"default"],[147750,3,0,1,"default"],[147825,5,0,1,"default"],[147900,2,0,1,"default"],[147975,8,0,1,"default"],[148050,11,0,1,"default"],[148200,9,0,1,"default"],[148350,9,0,1,"default"],[148500,3,0,1,"default"],[148650,12,0,1,"default"]],"changeTimeScale":false,"timeScale":[4,4],"bpm":200,"changeBPM":false},{"altAnim":false,"mustHitSection":true,"lengthInSteps":16,"typeOfSection":0,"sectionNotes":[[149100,4,0,1,"default"],[149250,13,0,1,"default"],[149550,10,0,1,"default"],[149700,11,0,1,"default"],[149850,1,0,1,"default"],[149925,4,0,1,"default"],[148800,5,0,1,"default"],[148950,11,0,1,"default"],[148875,8,0,1,"default"],[149025,9,0,1,"default"],[149175,6,0,1,"default"],[149775,8,0,1,"default"]],"changeTimeScale":false,"timeScale":[4,4],"bpm":200,"changeBPM":false},{"altAnim":false,"mustHitSection":true,"lengthInSteps":16,"typeOfSection":0,"sectionNotes":[[150000,11,0,1,"default"],[150075,13,0,1,"default"],[150150,3,0,1,"default"],[150225,5,0,1,"default"],[150300,2,0,1,"default"],[150375,8,0,1,"default"],[150450,11,0,1,"default"],[150600,9,0,1,"default"],[150750,9,0,1,"default"],[150900,3,0,1,"default"],[151050,12,0,1,"default"]],"changeTimeScale":false,"timeScale":[4,4],"bpm":200,"changeBPM":false},{"altAnim":false,"mustHitSection":true,"lengthInSteps":16,"typeOfSection":0,"sectionNotes":[[151500,4,0,0,"default"],[151650,13,0,0,"default"],[151950,10,0,0,"default"],[152100,11,0,0,"default"],[152250,1,0,0,"default"],[152325,4,0,0,"default"],[151200,5,0,0,"default"],[151275,9,0,1,"default"],[151350,14,0,1,"default"],[151425,10,0,1,"default"],[151575,8,0,1,"default"],[152175,7,0,1,"default"]],"changeTimeScale":false,"timeScale":[4,4],"bpm":200,"changeBPM":false},{"altAnim":false,"mustHitSection":true,"lengthInSteps":16,"typeOfSection":0,"sectionNotes":[[152400,11,0,0,"default"],[152475,13,0,0,"default"],[152550,3,0,0,"default"],[152625,5,0,0,"default"],[152700,2,0,0,"default"],[152775,8,0,0,"default"],[152850,11,0,0,"default"],[153000,9,0,0,"default"],[153150,9,0,0,"default"],[153300,3,0,0,"default"],[153450,12,0,0,"default"],[153375,5,0,1,"default"],[153525,10,0,1,"default"]],"changeTimeScale":false,"timeScale":[4,4],"bpm":200,"changeBPM":false},{"altAnim":false,"mustHitSection":true,"lengthInSteps":16,"typeOfSection":0,"sectionNotes":[[153600,10,2325,1,"default"]],"changeTimeScale":false,"timeScale":[4,4],"bpm":200,"changeBPM":false},{"altAnim":false,"mustHitSection":true,"lengthInSteps":16,"typeOfSection":0,"sectionNotes":[],"changeTimeScale":false,"timeScale":[4,4],"bpm":200,"changeBPM":false},{"altAnim":false,"mustHitSection":true,"lengthInSteps":16,"typeOfSection":0,"sectionNotes":[],"changeTimeScale":false,"timeScale":[4,4],"bpm":200,"changeBPM":false},{"altAnim":false,"mustHitSection":true,"lengthInSteps":16,"typeOfSection":0,"sectionNotes":[],"changeTimeScale":false,"timeScale":[4,4],"changeBPM":false,"bpm":200},{"altAnim":false,"mustHitSection":true,"lengthInSteps":16,"typeOfSection":0,"sectionNotes":[],"changeTimeScale":false,"timeScale":[4,4],"bpm":200,"changeBPM":false},{"altAnim":false,"mustHitSection":true,"lengthInSteps":16,"typeOfSection":0,"sectionNotes":[],"changeTimeScale":false,"timeScale":[4,4],"bpm":200,"changeBPM":false},{"altAnim":false,"mustHitSection":true,"lengthInSteps":16,"typeOfSection":0,"sectionNotes":[],"changeTimeScale":false,"timeScale":[4,4],"changeBPM":false,"bpm":200},{"altAnim":false,"mustHitSection":true,"lengthInSteps":16,"typeOfSection":0,"sectionNotes":[],"changeTimeScale":false,"timeScale":[4,4],"changeBPM":false,"bpm":200},{"altAnim":false,"mustHitSection":true,"lengthInSteps":16,"typeOfSection":0,"sectionNotes":[],"changeTimeScale":false,"timeScale":[4,4],"changeBPM":false,"bpm":200},{"altAnim":false,"mustHitSection":true,"lengthInSteps":16,"typeOfSection":0,"sectionNotes":[],"changeTimeScale":false,"timeScale":[4,4],"bpm":200,"changeBPM":false},{"altAnim":false,"mustHitSection":true,"lengthInSteps":16,"typeOfSection":0,"sectionNotes":[],"changeTimeScale":false,"timeScale":[4,4],"bpm":200,"changeBPM":false},{"altAnim":false,"mustHitSection":true,"lengthInSteps":16,"typeOfSection":0,"sectionNotes":[],"changeTimeScale":false,"timeScale":[4,4],"bpm":200,"changeBPM":false},{"altAnim":false,"mustHitSection":true,"lengthInSteps":16,"typeOfSection":0,"sectionNotes":[],"changeTimeScale":false,"timeScale":[4,4],"bpm":200,"changeBPM":false},{"altAnim":false,"mustHitSection":true,"lengthInSteps":16,"typeOfSection":0,"sectionNotes":[],"changeTimeScale":false,"timeScale":[4,4],"changeBPM":false,"bpm":200},{"altAnim":false,"mustHitSection":true,"lengthInSteps":16,"typeOfSection":0,"sectionNotes":[],"changeTimeScale":false,"timeScale":[4,4],"changeBPM":false,"bpm":200},{"altAnim":false,"mustHitSection":true,"lengthInSteps":16,"typeOfSection":0,"sectionNotes":[],"changeTimeScale":false,"timeScale":[4,4],"bpm":200,"changeBPM":false},{"altAnim":false,"mustHitSection":true,"lengthInSteps":16,"typeOfSection":0,"sectionNotes":[],"changeTimeScale":false,"timeScale":[4,4],"bpm":200,"changeBPM":false},{"altAnim":false,"mustHitSection":true,"lengthInSteps":16,"typeOfSection":0,"sectionNotes":[],"changeTimeScale":false,"timeScale":[4,4],"changeBPM":false,"bpm":200},{"altAnim":false,"mustHitSection":true,"lengthInSteps":16,"typeOfSection":0,"sectionNotes":[],"changeTimeScale":false,"timeScale":[4,4],"changeBPM":false,"bpm":200},{"altAnim":false,"mustHitSection":true,"lengthInSteps":16,"typeOfSection":0,"sectionNotes":[],"changeTimeScale":false,"timeScale":[4,4],"changeBPM":false,"bpm":200},{"altAnim":false,"mustHitSection":true,"lengthInSteps":16,"typeOfSection":0,"sectionNotes":[],"changeTimeScale":false,"timeScale":[4,4],"bpm":200,"changeBPM":false},{"altAnim":false,"mustHitSection":true,"lengthInSteps":16,"typeOfSection":0,"sectionNotes":[],"changeTimeScale":false,"timeScale":[4,4],"bpm":200,"changeBPM":false},{"altAnim":false,"mustHitSection":true,"lengthInSteps":16,"typeOfSection":0,"sectionNotes":[],"changeTimeScale":false,"timeScale":[4,4],"changeBPM":false,"bpm":200},{"altAnim":false,"mustHitSection":true,"lengthInSteps":16,"typeOfSection":0,"sectionNotes":[],"changeTimeScale":false,"timeScale":[4,4],"changeBPM":false,"bpm":200},{"altAnim":false,"mustHitSection":true,"lengthInSteps":16,"typeOfSection":0,"sectionNotes":[],"changeTimeScale":false,"timeScale":[4,4],"bpm":200,"changeBPM":false},{"altAnim":false,"mustHitSection":true,"lengthInSteps":16,"typeOfSection":0,"sectionNotes":[],"changeTimeScale":false,"timeScale":[4,4],"bpm":200,"changeBPM":false},{"altAnim":false,"mustHitSection":true,"lengthInSteps":16,"typeOfSection":0,"sectionNotes":[],"changeTimeScale":false,"timeScale":[4,4],"bpm":200,"changeBPM":false},{"altAnim":false,"mustHitSection":true,"lengthInSteps":16,"typeOfSection":0,"sectionNotes":[],"changeTimeScale":false,"timeScale":[4,4],"changeBPM":false,"bpm":200},{"altAnim":false,"mustHitSection":true,"lengthInSteps":16,"typeOfSection":0,"sectionNotes":[],"changeTimeScale":false,"timeScale":[4,4],"bpm":200,"changeBPM":false},{"lengthInSteps":16,"altAnim":false,"changeTimeScale":false,"typeOfSection":0,"sectionNotes":[],"bpm":200,"changeBPM":false,"timeScale":[4,4],"mustHitSection":true},{"lengthInSteps":16,"altAnim":false,"changeTimeScale":false,"typeOfSection":0,"sectionNotes":[],"bpm":200,"changeBPM":false,"timeScale":[4,4],"mustHitSection":true},{"lengthInSteps":16,"altAnim":false,"changeTimeScale":false,"typeOfSection":0,"sectionNotes":[],"bpm":200,"changeBPM":false,"timeScale":[4,4],"mustHitSection":true},{"lengthInSteps":16,"altAnim":false,"changeTimeScale":false,"typeOfSection":0,"sectionNotes":[],"bpm":200,"changeBPM":false,"timeScale":[4,4],"mustHitSection":true}],"player2":"sshaggybean","mania":15,"endCutscene":"","song":"mortem","validScore":true,"speed":3,"ui_Skin":"default","events":[],"cutscene":"","timescale":[4,4],"needsVoices":true,"stage":"asteroidfinale","gf":"gf","bpm":200}}